CHANGELOG.md
LICENSE
README.md
documentation/block.md
documentation/span.md
markdownio/__init__.py
markdownio/block.py
markdownio/markdownio.py
markdownio/span.py
markdownio-0.1.0.dist-info/LICENSE
markdownio-0.1.0.dist-info/WHEEL
markdownio-0.1.0.dist-info/METADATA
markdownio-0.1.0.dist-info/RECORD
