Metadata-Version: 2.1
Name: markdownio
Version: 0.1.0
Summary: Python tool to write Markdown as code easily.
Home-page: https://github.com/u8slvn/markdownio
License: MIT
Keywords: markdown,domain-specific-language,markup-language
Author: u8slvn
Author-email: u8slvn@gmail.com
Requires-Python: >=3.7,<4.0
Classifier: Development Status :: 5 - Production/Stable
Classifier: Intended Audience :: Developers
Classifier: License :: OSI Approved :: MIT License
Classifier: Natural Language :: English
Classifier: Programming Language :: Python
Classifier: Programming Language :: Python :: 3
Classifier: Programming Language :: Python :: 3.10
Classifier: Programming Language :: Python :: 3.7
Classifier: Programming Language :: Python :: 3.8
Classifier: Programming Language :: Python :: 3.9
Classifier: Topic :: Software Development :: Build Tools
Classifier: Topic :: Software Development :: Libraries :: Python Modules
Project-URL: Repository, https://github.com/u8slvn/markdownio
